{
  "showGettingStartedBanner": true,
  "hasMigratedDailyNoteSettings": true,
  "hasMigratedWeeklyNoteSettings": false,
  "daily": {
    "format": "DD MMM yyyy",
    "folder": "02 Execution/1 Daily",
    "template": "03 SaveBox/Templates/Daily Template",
    "enabled": true
  },
  "weekly": {
    "format": "",
    "template": "",
    "folder": ""
  },
  "monthly": {
    "format": "",
    "template": "",
    "folder": ""
  },
  "quarterly": {
    "format": "",
    "template": "",
    "folder": ""
  },
  "yearly": {
    "format": "",
    "template": "",
    "folder": ""
  }
}